docxcompose/__init__.py
docxcompose/command.py
docxcompose/composer.py
docxcompose/image.py
docxcompose/properties.py
docxcompose/sdt.py
docxcompose/utils.py
docxcompose/templates/custom.xml
docxcompose/templates/footer.xml
docxcompose/templates/footnotes.xml
docxcompose/templates/header.xml
docxcompose/templates/numbering.xml
docxcompose2-1.4.2.dist-info/LICENSE
docxcompose2-1.4.2.dist-info/METADATA
docxcompose2-1.4.2.dist-info/WHEEL
docxcompose2-1.4.2.dist-info/entry_points.txt
docxcompose2-1.4.2.dist-info/top_level.txt
docxcompose2-1.4.2.dist-info/zip-safe
docxcompose2-1.4.2.dist-info/RECORD
