Metadata-Version: 2.1
Name: docxcompose2
Version: 1.4.2
Summary: Compose .docx documents
Home-page: https://github.com/PasaOpasen/docxcompose2
Author: PasaOpasen
Author-email: qtckpuhdsa@gmail.com
License: MIT license
Keywords: Python DOCX Word OOXML (with bayoo-docx dependency)
Platform: UNKNOWN
Classifier: Programming Language :: Python
Classifier: Programming Language :: Python :: 2.7
Classifier: Programming Language :: Python :: 3
Classifier: Operating System :: OS Independent
Classifier: License :: OSI Approved :: MIT License
Requires-Dist: lxml
Requires-Dist: bayoo-docx>=0.2.20
Requires-Dist: setuptools
Requires-Dist: six
Requires-Dist: babel
Provides-Extra: test
Requires-Dist: pytest; extra == "test"
Provides-Extra: tests
Requires-Dist: pytest; extra == "tests"
